fiftyten_service_contracts/__init__.py
fiftyten_service_contracts/api_client.py
fiftyten_service_contracts/api_response.py
fiftyten_service_contracts/configuration.py
fiftyten_service_contracts/exceptions.py
fiftyten_service_contracts/py.typed
fiftyten_service_contracts/rest.py
fiftyten_service_contracts/api/__init__.py
fiftyten_service_contracts/api/default_api.py
fiftyten_service_contracts/models/__init__.py
fiftyten_service_contracts/models/api_health_get200_response.py
fiftyten_service_contracts/models/api_tasks_post_request.py
fiftyten_service_contracts/models/api_tasks_post_request_one_of.py
fiftyten_service_contracts/models/base_market_context.py
fiftyten_service_contracts/models/candle.py
fiftyten_service_contracts/models/candle_store.py
fiftyten_service_contracts/models/crypto_market_context.py
fiftyten_service_contracts/models/crypto_market_type.py
fiftyten_service_contracts/models/data_update_event.py
fiftyten_service_contracts/models/data_update_event_context.py
fiftyten_service_contracts/models/event_metadata.py
fiftyten_service_contracts/models/exchange_type.py
fiftyten_service_contracts/models/interval.py
fiftyten_service_contracts/models/load_context.py
fiftyten_service_contracts/models/symbol.py
fiftyten_service_contracts/models/task.py
fiftyten_service_contracts/models/task_result.py
fiftyten_service_contracts/models/worker_registration.py
fiftyten_service_contracts/models/worker_status.py
test/__init__.py
test/test_api_health_get200_response.py
test/test_api_tasks_post_request.py
test/test_api_tasks_post_request_one_of.py
test/test_base_market_context.py
test/test_candle.py
test/test_candle_store.py
test/test_crypto_market_context.py
test/test_crypto_market_type.py
test/test_data_update_event.py
test/test_data_update_event_context.py
test/test_default_api.py
test/test_event_metadata.py
test/test_exchange_type.py
test/test_interval.py
test/test_load_context.py
test/test_symbol.py
test/test_task.py
test/test_task_result.py
fiftyten_service_contracts-0.0.4.dist-info/METADATA
fiftyten_service_contracts-0.0.4.dist-info/WHEEL
fiftyten_service_contracts-0.0.4.dist-info/top_level.txt
fiftyten_service_contracts-0.0.4.dist-info/RECORD
