Metadata-Version: 2.4
Name: fiftyten-service-contracts
Version: 0.0.4
Summary: Shared type definitions and API contracts for FiftyTen microservices
Home-page: https://github.com/5010-dev/service-contracts
Author: FiftyTen
Classifier: Programming Language :: Python :: 3
Classifier: License :: OSI Approved :: MIT License
Classifier: Operating System :: OS Independent
Requires-Python: >=3.7
Requires-Dist: urllib3>=1.25.3
Requires-Dist: python-dateutil
Dynamic: author
Dynamic: classifier
Dynamic: description
Dynamic: description-content-type
Dynamic: home-page
Dynamic: requires-dist
Dynamic: requires-python
Dynamic: summary
